MANIFEST.in
README.md
setup.cfg
setup.py
src/coffee_compressor_compiler.egg-info/PKG-INFO
src/coffee_compressor_compiler.egg-info/SOURCES.txt
src/coffee_compressor_compiler.egg-info/dependency_links.txt
src/coffee_compressor_compiler.egg-info/not-zip-safe
src/coffee_compressor_compiler.egg-info/requires.txt
src/coffee_compressor_compiler.egg-info/top_level.txt
src/coffeecompressorcompiler/__init__.py
src/coffeecompressorcompiler/filter.py
src/coffeecompressorcompiler/js/coffee-script.js
src/coffeecompressorcompiler/js/compiler.js
src/tests/__init__.py
src/tests/compiler_test.py
src/tests/filter_test.py