Metadata-Version: 1.1
Name: coffee-compressor-compiler
Version: 0.2.0
Summary: django_compressor filter to compile coffee-script
Home-page: https://github.com/Juvenal1228/coffee-compressor-compiler
Author: Austin Morton
Author-email: amorton@juvsoft.com
License: MIT
Platform: UNKNOWN
Classifier: Framework :: Django
Classifier: Intended Audience :: Developers
Classifier: License :: OSI Approved :: MIT License
Classifier: Operating System :: OS Independent
Classifier: Programming Language :: Python
Classifier: Programming Language :: Python :: 2.6
Classifier: Programming Language :: Python :: 2.7
Classifier: Topic :: Internet :: WWW/HTTP
